setup.py
distributions_practice_OOP/Binomialdistribution.py
distributions_practice_OOP/Gaussiandistribution.py
distributions_practice_OOP/Generaldistribution.py
distributions_practice_OOP/__init__.py
distributions_practice_OOP.egg-info/PKG-INFO
distributions_practice_OOP.egg-info/SOURCES.txt
distributions_practice_OOP.egg-info/dependency_links.txt
distributions_practice_OOP.egg-info/not-zip-safe
distributions_practice_OOP.egg-info/top_level.txt